en_ud_model_sm/__init__.py
en_ud_model_sm/meta.json
en_ud_model_sm/en_ud_model_sm-1.1.0/meta.json
en_ud_model_sm/en_ud_model_sm-1.1.0/tokenizer
en_ud_model_sm/en_ud_model_sm-1.1.0/ner/cfg
en_ud_model_sm/en_ud_model_sm-1.1.0/ner/model
en_ud_model_sm/en_ud_model_sm-1.1.0/ner/moves
en_ud_model_sm/en_ud_model_sm-1.1.0/parser/cfg
en_ud_model_sm/en_ud_model_sm-1.1.0/parser/model
en_ud_model_sm/en_ud_model_sm-1.1.0/parser/moves
en_ud_model_sm/en_ud_model_sm-1.1.0/tagger/cfg
en_ud_model_sm/en_ud_model_sm-1.1.0/tagger/model
en_ud_model_sm/en_ud_model_sm-1.1.0/tagger/tag_map
en_ud_model_sm/en_ud_model_sm-1.1.0/vocab/key2row
en_ud_model_sm/en_ud_model_sm-1.1.0/vocab/lexemes.bin
en_ud_model_sm/en_ud_model_sm-1.1.0/vocab/lookups.bin
en_ud_model_sm/en_ud_model_sm-1.1.0/vocab/strings.json
en_ud_model_sm/en_ud_model_sm-1.1.0/vocab/vectors
en_ud_model_sm-1.1.0.dist-info/LICENSE
en_ud_model_sm-1.1.0.dist-info/METADATA
en_ud_model_sm-1.1.0.dist-info/WHEEL
en_ud_model_sm-1.1.0.dist-info/top_level.txt
en_ud_model_sm-1.1.0.dist-info/RECORD
